{
	"genericName": "Battlefield Medicine",
	"description": "Organic units will slowly regenerate health over time when idle.",
	"cost": {
		"food": 1000,
		"metal": 250
	},
	"requirements": { "tech": "phase_city" },
	"requirementsTooltip": "Unlocked in City Phase.",
	"icon": "asclepius_rod.png",
	"researchTime": 40,
	"tooltip": "Idle Organic units +0.5 health regeneration rate.",
	"modifications": [
		{ "value": "Health/IdleRegenRate", "add": 0.5 }
	],
	"affects": ["Unit Organic"],
	"soundComplete": "interface/alarm/alarm_upgradearmory.xml"
}
