<?xml version="1.0" encoding="utf-8"?>
<Entity parent="template_unit_mechanical_ship_trireme">
  <Cost>
    <BuildTime>40</BuildTime>
  </Cost>
  <Footprint>
    <Square width="12.0" depth="36.0"/>
    <Height>8.0</Height>
  </Footprint>
  <GarrisonHolder>
    <Max>40</Max>
  </GarrisonHolder>
  <Health>
    <Max op="add">200</Max>
  </Health>
  <Identity>
    <Civ>gaul</Civ>
    <SpecificName>Venetic Ponti</SpecificName>
    <Tooltip>Transport many soldiers across the sea.</Tooltip>
    <Icon>units/celt_ship_trireme.png</Icon>
  </Identity>
  <UnitMotion>
    <WalkSpeed op="mul">0.9</WalkSpeed>
    <Run>
      <Speed op="mul">0.9</Speed>
    </Run>
  </UnitMotion>
  <VisualActor>
    <Actor>structures/celts/warship.xml</Actor>
  </VisualActor>
</Entity>
