<?xml version="1.0" encoding="utf-8"?>
<Entity parent="units/hele_infantry_spearman_b">
  <Identity>
    <IconCell>4</IconCell>
  </Identity>
  <ResourceGatherer>
    <BaseSpeed>1.5</BaseSpeed>
  </ResourceGatherer>
  <Health>
    <Max>110</Max>
    <RegenRate>0.3</RegenRate>
  </Health>
  <Armour>
    <Hack>15.0</Hack>
    <Pierce>17.0</Pierce>
    <Crush>18.0</Crush>
  </Armour>
  <UnitMotion>
    <WalkSpeed>5.0</WalkSpeed>
  </UnitMotion>
  <Attack>
    <Hack>6.0</Hack>
    <Pierce>16.0</Pierce>
  </Attack>
  <VisualActor>
    <Actor>units/hellenes/infantry_spearman_a.xml</Actor>
  </VisualActor>
</Entity>
