<?xml version="1.0" encoding="UTF-8" standalone="no" ?>
<actor version="1">

  <castshadow/>

  <group>
    <variant frequency="1" name="large-short">
      <mesh>gaia/cross_large_short.pmd</mesh>
    </variant>
    <variant frequency="1" name="large-tall">
      <mesh>gaia/cross_large_tall.pmd</mesh>
    </variant>
    <variant frequency="1" name="large-angled">
      <mesh>gaia/cross_angledfromtop.pmd</mesh>
    </variant>
  </group>

  <group>
    <variant frequency="10" name="White / Daisy">
      <texture>gaia/grass_field_flowering_tall_a.dds</texture>
    </variant>
    <variant frequency="5" name="Red / Poppy">
      <texture>gaia/grass_field_flowering_tall_red.dds</texture>
    </variant>
    <variant frequency="5" name="Yellow">
      <texture>gaia/grass_field_flowering_tall_yellow.dds</texture>
    </variant>
    <variant frequency="2" name="Violet">
      <texture>gaia/grass_field_flowering_tall_violet.dds</texture>
    </variant>
  </group>

  <material>basic_trans.xml</material>

</actor>
