<?xml version="1.0" encoding="utf-8"?>
<actor version="1">
  <castshadow/>
  <group>
    <variant>
      <mesh>props/ptol_settlement_outpost.dae</mesh>
      <props>
        <prop actor="props/structures/ptolemies/settlement_outpost_props.xml" attachpoint="root"/>
      </props>      
      <textures>
        <texture file="props/scaffold.png" name="baseTex"/>
        <texture file="structural/ao/ptol_settlement.png" name="aoTex"/>
      </textures>
    </variant>
  </group>
  <material>no_trans_ao.xml</material>  
</actor>
