<?xml version="1.0" encoding="utf-8"?>
<actor version="1">
  <castshadow/>
  <group>
    <variant>
      <mesh>structural/iber_merch.dae</mesh>
      <props>
        <prop actor="props/structures/iberians/merch_sail.xml" attachpoint="root"/>
      </props>
      <textures>
        <texture file="structural/iber_ship.dds" name="baseTex"/>
        <texture file="default_norm.png" name="normTex"/>
        <texture file="null_black.dds" name="specTex"/>
      </textures>
    </variant>
  </group>
  <group>
    <variant frequency="0" name="garrisoned">
      <props>
        <prop actor="props/special/common/garrison_flag_iber.xml" attachpoint="garrisoned"/>
      </props>
    </variant>
    <variant frequency="1" name="ungarrisoned"/>
  </group>
  <material>player_trans_norm_spec.xml</material>
</actor>
