<?xml version="1.0" encoding="utf-8"?>
<actor version="1">
  <castshadow/>
  <group>
    <variant name="Apulo-Boeotian">
      <mesh>props/helmet/rome_apulo_a.dae</mesh>
      <textures>
        <texture file="props/helmet/rome_apulo_boeotian_01_bronze.png" name="baseTex"/>
        <texture file="props/helmet/rome_apulo_boeotian_01_norm.png" name="normTex"/>
        <texture file="props/helmet/rome_apulo_boeotian_01_spec.png" name="specTex"/>
      </textures>
    </variant>
  </group>
  <group>
    <variant name="Triple Feather">
      <props>
        <prop actor="props/units/helmets/props/helmet_feather_a.xml" attachpoint="feather_L"/>
        <prop actor="props/units/helmets/props/helmet_feather_a.xml" attachpoint="feather_R"/>
        <prop actor="props/units/helmets/props/helmet_feather_a.xml" attachpoint="crest"/>
      </props>
    </variant>
    <variant name="Crest + Feather">
      <props>
        <prop actor="props/units/helmets/props/helmet_feather_a.xml" attachpoint="feather_L"/>
        <prop actor="props/units/helmets/props/helmet_feather_a.xml" attachpoint="feather_R"/>
      </props>
    </variant>
  </group>
  <material>basic_trans_parallax_spec.xml</material>
</actor>
