<?xml version="1.0" encoding="utf-8"?>
<actor version="1">
  <castshadow/>
  <group>
    <variant frequency="1" name="Base">
      <mesh>props/new/capes/cape_hd_hoplite.dae</mesh>
    </variant>
  </group>
  <group>
    <variant frequency="1" name="Normal cape">
      <textures>
        <texture file="props/cape_hd.dds" name="baseTex"/>
      </textures>
    </variant>
    <variant frequency="1" name="Celtic cape 01">
      <textures>
        <texture file="props/cape_celt_01.png" name="baseTex"/>
      </textures>
    </variant>
    <variant frequency="1" name="Celtic cape 02">
      <textures>
        <texture file="props/cape_celt_02.png" name="baseTex"/>
      </textures>
    </variant>
    <variant frequency="1" name="Celtic cape 03">
      <textures>
        <texture file="props/cape_celt_03.png" name="baseTex"/>
      </textures>
    </variant>
    <variant frequency="1" name="Celtic cape 04">
      <textures>
        <texture file="props/cape_celt_04.png" name="baseTex"/>
      </textures>
    </variant>
    <variant frequency="1" name="Celtic cape 05">
      <textures>
        <texture file="props/cape_celt_05.png" name="baseTex"/>
      </textures>
    </variant>
    <variant frequency="1" name="Celtic cape 06">
      <textures>
        <texture file="props/cape_celt_06.png" name="baseTex"/>
      </textures>
    </variant>
    <variant frequency="1" name="Celtic cape 07">
      <textures>
        <texture file="props/cape_celt_07.png" name="baseTex"/>
      </textures>
    </variant>
  </group>
  <group>
    <variant file="biped/base_swordsman_shield_relax.xml"/>
    <variant file="biped/carry_food.xml"/>
    <variant file="biped/carry_meat.xml"/>
    <variant file="biped/carry_wood.xml"/>
    <variant file="biped/carry_stone.xml"/>
    <variant file="biped/carry_metal.xml"/>
  </group>
  <group>
    <variant frequency="1" name="Idle"/>
    <variant file="biped/attack_capture.xml"/>
    <variant file="biped/attack_slaughter.xml"/>
    <variant file="biped/gather_tree.xml"/>
    <variant file="biped/gather_grain.xml"/>
    <variant file="biped/gather_fruit.xml"/>
    <variant file="biped/gather_meat.xml"/>
    <variant file="biped/gather_rock.xml"/>
    <variant file="biped/gather_ore.xml"/>
    <variant file="biped/gather_ruins.xml"/>
    <variant file="biped/gather_praise.xml"/>
    <variant file="biped/build.xml"/>
    <variant file="biped/build_farm.xml"/>
    <variant file="biped/death_infantry.xml"/>
  </group>
  <material>player_trans.xml</material>
</actor>
