<?xml version="1.0" encoding="UTF-8"?>
<variant name="gather_praise">
  <animations>
    <animation file="biped/citizen/pray.dae" name="gather_praise" id="praise1" speed="100"/>
    <animation file="biped/citizen/pray.dae" name="gather_praise" id="praise2" speed="200"/>
    <animation file="biped/citizen/pray.dae" name="gather_praise" id="praise3" speed="50"/>
  </animations>
  <props>
    <prop attachpoint="weapon_R"/>
    <prop attachpoint="weapon_L"/>
    <prop attachpoint="weapon_bow"/>
    <prop attachpoint="shield"/>
    <prop attachpoint="shield_arm"/>
    <prop attachpoint="ammo"/>
  </props>
</variant>
