<?xml version="1.0" encoding="UTF-8" standalone="no" ?>
<actor version="1">
  <castshadow/>
  <group>
    <variant>
      <mesh>structural/celt_wt.dae</mesh>
      <props>
        <prop actor="props/structures/celts/wall_turret.xml" attachpoint="props_main"/>
        <prop actor="props/units/weapons/arrow_front.xml" attachpoint="projectile"/>
      </props>
      <texture>structural/celt_wall.dds</texture>
    </variant>
  </group>
  <group>
    <variant frequency="100" name="Idle"/>
    <variant name="death">
      <props>
        <prop actor="particle/destruction_smoke_small.xml" attachpoint="root"/>
        <prop actor="particle/destruction_dust_small.xml" attachpoint="root"/>
        <prop actor="particle/destruction_dust_small_gray.xml" attachpoint="root"/>
      </props>
    </variant>
  </group>
</actor>
