<?xml version="1.0" encoding="utf-8" standalone="no"?>
<!DOCTYPE Scenario SYSTEM "/maps/scenario_v4.dtd">

<Scenario>
	<Environment>
		<SunColour r="1" g="1" b="1" />
		<SunElevation angle="0.785398" />
		<SunRotation angle="4.71239" />
		<TerrainAmbientColour r="0" g="0" b="0" />
		<UnitsAmbientColour r="0.4" g="0.4" b="0.4" />
	</Environment>
	<Entities>
		<Entity>
			<Template>celt_isp_b</Template>
			<Player>1</Player>
			<Position x="35.1084" y="54.6241" z="26.441" />
			<Orientation angle="1.50083" />
		</Entity>
		<Entity>
			<Template>celt_isp_a</Template>
			<Player>1</Player>
			<Position x="34.2309" y="55.5514" z="34.6702" />
			<Orientation angle="2.10087" />
		</Entity>
		<Entity>
			<Template>celt_isp_e</Template>
			<Player>1</Player>
			<Position x="35.1859" y="54.0283" z="22.1629" />
			<Orientation angle="2.13893" />
		</Entity>
		<Entity>
			<Template>hele_isp_b</Template>
			<Player>2</Player>
			<Position x="64.9301" y="63.1704" z="41.7311" />
			<Orientation angle="-2.32436" />
		</Entity>
		<Entity>
			<Template>hele_iar_b</Template>
			<Player>2</Player>
			<Position x="73.7439" y="65.0304" z="41.037" />
			<Orientation angle="3.05388" />
		</Entity>
		<Entity>
			<Template>hele_isp_b</Template>
			<Player>2</Player>
			<Position x="71.1476" y="64.3086" z="37.1003" />
			<Orientation angle="3.02656" />
		</Entity>
		<Entity>
			<Template>hele_fem</Template>
			<Player>2</Player>
			<Position x="68.4374" y="64.022" z="43.992" />
			<Orientation angle="-3.06105" />
		</Entity>
		<Entity>
			<Template>wrld_flora_pine</Template>
			<Player>0</Player>
			<Position x="15.3714" y="50.7793" z="8.48827" />
			<Orientation angle="-1.91413" />
		</Entity>
		<Entity>
			<Template>wrld_flora_pine</Template>
			<Player>0</Player>
			<Position x="17.0449" y="52.1763" z="19.6513" />
			<Orientation angle="-1.47775" />
		</Entity>
		<Entity>
			<Template>wrld_flora_pine</Template>
			<Player>0</Player>
			<Position x="18.1181" y="53.7348" z="31.7626" />
			<Orientation angle="-2.40597" />
		</Entity>
		<Entity>
			<Template>wrld_flora_pine</Template>
			<Player>0</Player>
			<Position x="28.3413" y="52.9118" z="23.3762" />
			<Orientation angle="-2.0717" />
		</Entity>
		<Entity>
			<Template>wrld_flora_pine</Template>
			<Player>0</Player>
			<Position x="30.3215" y="52.4484" z="15.9086" />
			<Orientation angle="-1.89066" />
		</Entity>
		<Entity>
			<Template>wrld_flora_pine</Template>
			<Player>0</Player>
			<Position x="25.3501" y="51.0897" z="8.98334" />
			<Orientation angle="-1.93184" />
		</Entity>
		<Entity>
			<Template>wrld_flora_pine</Template>
			<Player>0</Player>
			<Position x="36.7198" y="52.7157" z="4.92175" />
			<Orientation angle="-2.61247" />
		</Entity>
		<Entity>
			<Template>wrld_flora_pine</Template>
			<Player>0</Player>
			<Position x="45.1813" y="56.1303" z="10.8454" />
			<Orientation angle="-2.20954" />
		</Entity>
		<Entity>
			<Template>wrld_rock_light</Template>
			<Player>0</Player>
			<Position x="81.6503" y="66.6198" z="38.0794" />
			<Orientation angle="-1.40624" />
		</Entity>
		<Entity>
			<Template>wrld_rock_light</Template>
			<Player>0</Player>
			<Position x="80.9813" y="66.6147" z="42.0556" />
			<Orientation angle="-0.96972" />
		</Entity>
		<Entity>
			<Template>wrld_rock_light</Template>
			<Player>0</Player>
			<Position x="87.485" y="67.7955" z="36.3964" />
			<Orientation angle="-1.1358" />
		</Entity>
		<Entity>
			<Template>wrld_rock_light</Template>
			<Player>0</Player>
			<Position x="84.5481" y="67.1066" z="32.9332" />
			<Orientation angle="-1.79328" />
		</Entity>
		<Entity>
			<Template>wrld_rock_light</Template>
			<Player>0</Player>
			<Position x="78.8986" y="65.9459" z="35.3864" />
			<Orientation angle="-1.76044" />
		</Entity>
		<Entity>
			<Template>wrld_rock_light</Template>
			<Player>0</Player>
			<Position x="86.442" y="67.7687" z="42.8618" />
			<Orientation angle="-0.333362" />
		</Entity>
		<Entity>
			<Template>wrld_rock_light</Template>
			<Player>0</Player>
			<Position x="81.2877" y="66.812" z="45.4815" />
			<Orientation angle="-0.678936" />
		</Entity>
		<Entity>
			<Template>wrld_rock_light</Template>
			<Player>0</Player>
			<Position x="74.9919" y="65.4297" z="44.3993" />
			<Orientation angle="0.337941" />
		</Entity>
		<Entity>
			<Template>wrld_rock_light</Template>
			<Player>0</Player>
			<Position x="77.2324" y="65.9574" z="45.6889" />
			<Orientation angle="-0.849893" />
		</Entity>
		<Entity>
			<Template>wrld_rock_light</Template>
			<Player>0</Player>
			<Position x="90.1107" y="68.2697" z="31.6646" />
			<Orientation angle="-1.95534" />
		</Entity>
		<Entity>
			<Template>wrld_rock_light</Template>
			<Player>0</Player>
			<Position x="91.42" y="68.58" z="36.0408" />
			<Orientation angle="-0.677787" />
		</Entity>
		<Entity>
			<Template>wrld_rock_light</Template>
			<Player>0</Player>
			<Position x="91.4276" y="68.6549" z="40.1847" />
			<Orientation angle="-1.06151" />
		</Entity>
		<Entity>
			<Template>wrld_rock_light</Template>
			<Player>0</Player>
			<Position x="84.9641" y="67.3804" z="40.2739" />
			<Orientation angle="-2.81858" />
		</Entity>
		<Entity>
			<Template>wrld_rock_light</Template>
			<Player>0</Player>
			<Position x="85.0381" y="67.6524" z="46.8461" />
			<Orientation angle="-2.94801" />
		</Entity>
		<Entity>
			<Template>wrld_flora_berrybush</Template>
			<Player>0</Player>
			<Position x="50.9975" y="60.6948" z="47.1002" />
			<Orientation angle="-1.04184" />
		</Entity>
		<Entity>
			<Template>wrld_flora_berrybush</Template>
			<Player>0</Player>
			<Position x="51.6084" y="61.1638" z="51.9146" />
			<Orientation angle="-0.56518" />
		</Entity>
		<Entity>
			<Template>wrld_flora_berrybush</Template>
			<Player>0</Player>
			<Position x="56.5408" y="61.7226" z="46.5217" />
			<Orientation angle="-0.901823" />
		</Entity>
		<Entity>
			<Template>wrld_flora_berrybush</Template>
			<Player>0</Player>
			<Position x="52.1532" y="60.5066" z="41.6767" />
			<Orientation angle="-1.44669" />
		</Entity>
		<Entity>
			<Template>wrld_flora_oak</Template>
			<Player>0</Player>
			<Position x="7.69094" y="50.3172" z="4.14664" />
			<Orientation angle="-1.45432" />
		</Entity>
		<Entity>
			<Template>wrld_flora_oak</Template>
			<Player>0</Player>
			<Position x="6.20238" y="52.1022" z="21.2296" />
			<Orientation angle="-1.63348" />
		</Entity>
		<Entity>
			<Template>wrld_flora_oak</Template>
			<Player>0</Player>
			<Position x="23.9856" y="50.807" z="2.70553" />
			<Orientation angle="-1.92181" />
		</Entity>
		<Entity>
			<Template>celt_cjv_a</Template>
			<Player>1</Player>
			<Position x="44.2417" y="61.4935" z="72.8738" />
			<Orientation angle="-2.82024" />
		</Entity>
		<Entity>
			<Template>celt_csw_a</Template>
			<Player>1</Player>
			<Position x="57.6615" y="63.0412" z="67.8101" />
			<Orientation angle="-2.92705" />
		</Entity>
		<Entity>
			<Template>celt_csp_b</Template>
			<Player>1</Player>
			<Position x="48.7094" y="61.7867" z="68.1292" />
			<Orientation angle="-2.8511" />
		</Entity>
		<Entity>
			<Template>celt_cjv_e</Template>
			<Player>1</Player>
			<Position x="102.1" y="70.5799" z="34.7825" />
			<Orientation angle="-3.13826" />
		</Entity>
		<Entity>
			<Template>celt_cjv_b</Template>
			<Player>1</Player>
			<Position x="97.6954" y="69.7796" z="42.4194" />
			<Orientation angle="-3.13769" />
		</Entity>
		<Entity>
			<Template>celt_cjv_a</Template>
			<Player>1</Player>
			<Position x="103.329" y="70.6209" z="40.9826" />
			<Orientation angle="-2.86647" />
		</Entity>
		<Entity>
			<Template>celt_cc</Template>
			<Player>1</Player>
			<Position x="10.4647" y="54.4342" z="57.4006" />
			<Orientation angle="-2.99394" />
		</Entity>
		<Entity>
			<Template>hele_cc</Template>
			<Player>1</Player>
			<Position x="79.7763" y="63.7998" z="14.1304" />
			<Orientation angle="-3.04106" />
		</Entity>
		<Entity>
			<Template>celt_ijv_e</Template>
			<Player>1</Player>
			<Position x="99.965" y="67.859" z="11.97" />
			<Orientation angle="-3.14159" />
		</Entity>
		<Entity>
			<Template>celt_ijv_b</Template>
			<Player>1</Player>
			<Position x="98.5025" y="67.4791" z="8.23869" />
			<Orientation angle="-2.94681" />
		</Entity>
		<Entity>
			<Template>celt_ijv_a</Template>
			<Player>1</Player>
			<Position x="94.6879" y="66.2072" z="6.38351" />
			<Orientation angle="-3.14159" />
		</Entity>
		<Entity>
			<Template>hele_iar_a</Template>
			<Player>1</Player>
			<Position x="38.305" y="61.2212" z="48.8122" />
			<Orientation angle="-3.09133" />
		</Entity>
		<Entity>
			<Template>hele_iar_b</Template>
			<Player>1</Player>
			<Position x="39.3182" y="61.3873" z="51.6087" />
			<Orientation angle="-2.99394" />
		</Entity>
		<Entity>
			<Template>hele_iar_e</Template>
			<Player>1</Player>
			<Position x="39.4323" y="61.3977" z="54.7539" />
			<Orientation angle="-2.94681" />
		</Entity>
		<Entity>
			<Template>celt_ijv_e</Template>
			<Player>1</Player>
			<Position x="103.746" y="69.6184" z="7.80956" />
			<Orientation angle="2.21168" />
		</Entity>
		<Entity>
			<Template>celt_ijv_e</Template>
			<Player>1</Player>
			<Position x="105.23" y="70.2382" z="11.1678" />
			<Orientation angle="2.79602" />
		</Entity>
		<Entity>
			<Template>celt_ijv_e</Template>
			<Player>1</Player>
			<Position x="107.866" y="71.5554" z="7.92635" />
			<Orientation angle="2.60124" />
		</Entity>
		<Entity>
			<Template>celt_ijv_b</Template>
			<Player>1</Player>
			<Position x="106.166" y="70.732" z="3.70653" />
			<Orientation angle="0.637743" />
		</Entity>
		<Entity>
			<Template>hele_isp_b</Template>
			<Player>1</Player>
			<Position x="117.659" y="68.5971" z="55.0333" />
			<Orientation angle="-3.14159" />
		</Entity>
		<Entity>
			<Template>hele_isp_a</Template>
			<Player>1</Player>
			<Position x="120.883" y="67.63" z="55.3301" />
			<Orientation angle="-2.94367" />
		</Entity>
		<Entity>
			<Template>hele_isp_e</Template>
			<Player>1</Player>
			<Position x="124.343" y="66.9636" z="55.7404" />
			<Orientation angle="-2.94367" />
		</Entity>
		<Entity>
			<Template>hele_isp_e</Template>
			<Player>1</Player>
			<Position x="123.524" y="65.0148" z="61.1849" />
			<Orientation angle="-3.14159" />
		</Entity>
		<Entity>
			<Template>hele_isp_e</Template>
			<Player>1</Player>
			<Position x="122.87" y="63.2224" z="66.9883" />
			<Orientation angle="-3.14159" />
		</Entity>
		<Entity>
			<Template>hele_isp_a</Template>
			<Player>1</Player>
			<Position x="119.777" y="66.1206" z="60.2513" />
			<Orientation angle="-2.94367" />
		</Entity>
		<Entity>
			<Template>hele_isp_a</Template>
			<Player>1</Player>
			<Position x="118.601" y="64.8098" z="65.7569" />
			<Orientation angle="-2.89655" />
		</Entity>
		<Entity>
			<Template>hele_isp_b</Template>
			<Player>1</Player>
			<Position x="116.098" y="67.287" z="59.7197" />
			<Orientation angle="-3.14159" />
		</Entity>
		<Entity>
			<Template>hele_isp_b</Template>
			<Player>1</Player>
			<Position x="115.014" y="66.0863" z="64.8292" />
			<Orientation angle="-3.14159" />
		</Entity>
		<Entity>
			<Template>celt_ijv_a</Template>
			<Player>1</Player>
			<Position x="93.5363" y="65.9301" z="2.80088" />
			<Orientation angle="-3.14159" />
		</Entity>
		<Entity>
			<Template>celt_ijv_a</Template>
			<Player>1</Player>
			<Position x="97.8894" y="67.201" z="3.63671" />
			<Orientation angle="-2.84628" />
		</Entity>
		<Entity>
			<Template>celt_ijv_a</Template>
			<Player>1</Player>
			<Position x="96.4884" y="65.8846" z="0.676216" />
			<Orientation angle="-2.89655" />
		</Entity>
		<Entity>
			<Template>celt_ijv_b</Template>
			<Player>1</Player>
			<Position x="101.554" y="68.7135" z="5.18676" />
			<Orientation angle="-3.14159" />
		</Entity>
		<Entity>
			<Template>celt_ijv_b</Template>
			<Player>1</Player>
			<Position x="102.259" y="68.7672" z="1.60387" />
			<Orientation angle="-3.14159" />
		</Entity>
		<Entity>
			<Template>celt_ijv_b</Template>
			<Player>1</Player>
			<Position x="95.2021" y="66.0063" z="13.0314" />
			<Orientation angle="-3.14159" />
		</Entity>
		<Entity>
			<Template>hele_ijv_e</Template>
			<Player>1</Player>
			<Position x="55.6155" y="59.7909" z="22.6904" />
			<Orientation angle="2.5462" />
		</Entity>
	</Entities>
	<Nonentities />
</Scenario>